[
  {
    "id": 1,
    "name": "Laptop Dell XPS 13",
    "price": 32990000.00,
    "description": "Laptop Dell XPS 13 inch, CPU Intel Core i7, RAM 16GB, SSD 512GB",
    "stockQuantity": 15,
    "status": "active",
    "createdAt": "2025-08-01T10:20:30Z",
    "updatedAt": "2025-08-05T14:10:00Z"
  },
  {
    "id": 2,
    "name": "iPhone 15 Pro Max",
    "price": 34990000.00,
    "description": "Điện thoại Apple iPhone 15 Pro Max, bộ nhớ 256GB, màu Titan Blue",
    "stockQuantity": 30,
    "status": "active",
    "createdAt": "2025-08-02T09:15:00Z",
    "updatedAt": "2025-08-06T16:30:00Z"
  },
  {
    "id": 3,
    "name": "Tai nghe Sony WH-1000XM5",
    "price": 8990000.00,
    "description": "Tai nghe chống ồn Sony WH-1000XM5, kết nối Bluetooth, pin 30 giờ",
    "stockQuantity": 25,
    "status": "active",
    "createdAt": "2025-08-03T11:45:20Z",
    "updatedAt": "2025-08-07T13:20:00Z"
  },
  {
    "id": 4,
    "name": "Chuột Logitech MX Master 3S",
    "price": 2490000.00,
    "description": "Chuột không dây Logitech MX Master 3S, DPI 8000, sạc USB-C",
    "stockQuantity": 40,
    "status": "active",
    "createdAt": "2025-08-04T08:00:00Z",
    "updatedAt": "2025-08-08T12:15:00Z"
  },
  {
    "id": 5,
    "name": "Bàn phím cơ Keychron K8 Pro",
    "price": 2990000.00,
    "description": "Bàn phím cơ không dây Keychron K8 Pro, switch Gateron Brown",
    "stockQuantity": 50,
    "status": "inactive",
    "createdAt": "2025-08-05T07:30:00Z",
    "updatedAt": "2025-08-09T09:45:00Z"
  },
  {
    "id": 6,
    "name": "Màn hình LG UltraFine 5K",
    "price": 18990000.00,
    "description": "Màn hình LG UltraFine 5K 27 inch, hỗ trợ Thunderbolt 3",
    "stockQuantity": 12,
    "status": "active",
    "createdAt": "2025-08-06T10:40:00Z",
    "updatedAt": "2025-08-10T11:30:00Z"
  },
  {
    "id": 7,
    "name": "Ổ cứng SSD Samsung 990 Pro 2TB",
    "price": 7490000.00,
    "description": "Ổ cứng SSD NVMe Samsung 990 Pro dung lượng 2TB, tốc độ đọc 7450MB/s",
    "stockQuantity": 20,
    "status": "active",
    "createdAt": "2025-08-07T09:00:00Z",
    "updatedAt": "2025-08-11T14:00:00Z"
  },
  {
    "id": 8,
    "name": "Máy ảnh Canon EOS R6 Mark II",
    "price": 58990000.00,
    "description": "Máy ảnh mirrorless Canon EOS R6 Mark II, cảm biến Full-Frame",
    "stockQuantity": 8,
    "status": "active",
    "createdAt": "2025-08-08T15:20:00Z",
    "updatedAt": "2025-08-12T09:50:00Z"
  },
  {
    "id": 9,
    "name": "Loa Bluetooth JBL Charge 5",
    "price": 3990000.00,
    "description": "Loa Bluetooth JBL Charge 5, chống nước IP67, pin 20 giờ",
    "stockQuantity": 60,
    "status": "active",
    "createdAt": "2025-08-09T13:10:00Z",
    "updatedAt": "2025-08-12T10:20:00Z"
  },
  {
    "id": 10,
    "name": "Máy lọc không khí Sharp FP-J60E-W",
    "price": 6990000.00,
    "description": "Máy lọc không khí Sharp FP-J60E-W, diện tích lọc 48m², Plasmacluster Ion",
    "stockQuantity": 18,
    "status": "inactive",
    "createdAt": "2025-08-10T08:15:00Z",
    "updatedAt": "2025-08-12T11:00:00Z"
  }
]
